__init__.py
agent_runner.py
custom_agent.py
main.py
org_agent.py
themes.py
ui.py
agent/__init__.py
agent/browser_agent.py
agent/browser_agent_output.py
agent/browser_massage_manager.py
agent/browser_system_prompts.py
browser/__init__.py
browser/custom_browser.py
browser/custom_context.py
components/agent_settings.py
components/browser_settings.py
components/header.py
components/llm_configuration.py
components/recordings.py
components/task_settings.py
controller/__init__.py
controller/custom_controller.py
utils/__init__.py
utils/utils.py
browser_use_webui_multimodel-0.1.0.dist-info/LICENSE
browser_use_webui_multimodel-0.1.0.dist-info/METADATA
browser_use_webui_multimodel-0.1.0.dist-info/WHEEL
browser_use_webui_multimodel-0.1.0.dist-info/top_level.txt
browser_use_webui_multimodel-0.1.0.dist-info/RECORD
