Metadata-Version: 2.1
Name: browser-use-webui-multimodel
Version: 0.1.0
Summary: browser-use-webui for multi ai models
Requires-Python: >=3.12
License-File: LICENSE
Requires-Dist: browser-use>=0.1.17
Requires-Dist: gradio>=5.10.0
Requires-Dist: langchain-google-genai>=2.0.8
Requires-Dist: langchain-ollama>=0.2.2
Requires-Dist: playwright>=1.49.1
Requires-Dist: pyperclip>=1.9.0
Requires-Dist: python-dotenv>=1.0.1
